frequenz/client/base/__init__.py
frequenz/client/base/authentication.py
frequenz/client/base/channel.py
frequenz/client/base/client.py
frequenz/client/base/conftest.py
frequenz/client/base/conversion.py
frequenz/client/base/exception.py
frequenz/client/base/py.typed
frequenz/client/base/retry.py
frequenz/client/base/signing.py
frequenz/client/base/streaming.py
frequenz_client_base-0.11.2.dist-info/licenses/LICENSE
frequenz_client_base-0.11.2.dist-info/METADATA
frequenz_client_base-0.11.2.dist-info/WHEEL
frequenz_client_base-0.11.2.dist-info/top_level.txt
frequenz_client_base-0.11.2.dist-info/RECORD
